alert/__init__.py
alert/admin.py
alert/alerts.py
alert/backends.py
alert/compat.py
alert/example_alerts.py
alert/exceptions.py
alert/forms.py
alert/listeners.py
alert/managers.py
alert/models.py
alert/signals.py
alert/utils.py
alert/management/__init__.py
alert/management/commands/__init__.py
alert/management/commands/send_alerts.py
alert/migrations/0001_initial.py
alert/migrations/0002_auto__add_field_alert_site.py
alert/migrations/0003_auto__add_adminalert.py
alert/migrations/0004_auto__add_field_adminalert_recipients.py
alert/migrations/__init__.py
alert/templates/alerts/base_email_body.html
alert/templates/alerts/DjangoAdminAlert/body.html
alert/templates/alerts/DjangoAdminAlert/title.html
django_alert-0.8.1.dist-info/DESCRIPTION.rst
django_alert-0.8.1.dist-info/METADATA
django_alert-0.8.1.dist-info/metadata.json
django_alert-0.8.1.dist-info/RECORD
django_alert-0.8.1.dist-info/top_level.txt
django_alert-0.8.1.dist-info/WHEEL
