Metadata-Version: 2.0
Name: django-alert
Version: 0.8.1
Summary: Send alerts, notifications, and messages based on events in your django application
Home-page: https://djangoalert.com
Author: James Robert
Author-email: jiaaro@gmail.com
License: MIT
Keywords: django alerts notifications social
Platform: UNKNOWN
Classifier: Development Status :: 5 - Production/Stable
Classifier: License :: OSI Approved :: MIT License
Classifier: Programming Language :: Python
Classifier: Framework :: Django
Classifier: Environment :: Web Environment
Classifier: Intended Audience :: Developers
Classifier: Operating System :: OS Independent
Classifier: Topic :: Internet :: WWW/HTTP
Classifier: Topic :: Utilities
Requires-Dist: django (>=1.4)
